sandstorm/__init__.py
sandstorm/config.py
sandstorm/decorators.py
sandstorm/errors.py
sandstorm/handlers.py
sandstorm/requests.py
sandstorm/server.py
sandstorm/utils.py
sandstorm/commands/__init__.py
sandstorm/commands/server.py
sandstorm/commands/shell.py
sandstorm/middlewares/__init__.py
sandstorm/middlewares/browserid.py
sandstorm/middlewares/core.py
sandstorm/middlewares/errors.py
sandstorm/middlewares/renderers.py
sandstorm/middlewares/responses.py
sandstorm/middlewares/transaction.py
sandstorm/middlewares/validators.py
sandstorm/registries/__init__.py
sandstorm/registries/core.py
sandstorm/registries/dummy.py
sandstorm/registries/errors.py
sandstorm/registries/interfaces.py
sandstorm/registries/managers.py
sandstorm/registries/tests/__init__.py
sandstorm/registries/tests/test_managers.py
sandstorm/registries/tests/test_packages.py
sandstorm/tests/__init__.py
sandstorm/tests/test_requests.py
sandstorm/tests/test_utils.py
sandstorm-0.1.5.dist-info/DESCRIPTION.rst
sandstorm-0.1.5.dist-info/entry_points.txt
sandstorm-0.1.5.dist-info/METADATA
sandstorm-0.1.5.dist-info/metadata.json
sandstorm-0.1.5.dist-info/RECORD
sandstorm-0.1.5.dist-info/top_level.txt
sandstorm-0.1.5.dist-info/WHEEL
