Metadata-Version: 2.0
Name: sandstorm
Version: 0.1.5
Summary: sandstorm
Home-page: https://github.com/TakesxiSximada/sandstorm
Author: TakesxiSximada
Author-email: takesxi.sximada@gmail.com
License: See http://www.python.org/3.4/license.html
Download-URL: https://github.com/TakesxiSximada/sandstorm
Platform: any
Classifier: Development Status :: 1 - Planning
Classifier: Intended Audience :: Developers
Classifier: Intended Audience :: Information Technology
Classifier: Intended Audience :: System Administrators
Classifier: Natural Language :: English
Classifier: Operating System :: MacOS :: MacOS X
Classifier: Operating System :: Microsoft :: Windows
Classifier: Operating System :: POSIX
Classifier: Programming Language :: Python :: 3.4
Requires: pyramid
Requires: tornado
Requires: transaction
Requires: azoth
Requires: jumon
Requires: jsonschema
Requires-Dist: pyramid
Requires-Dist: tornado
Requires-Dist: transaction
Requires-Dist: azoth
Requires-Dist: jumon
Requires-Dist: jsonschema
